MANIFEST.in
README.txt
setup.py
sdelib/Example1.py
sdelib/Operation.jpg
sdelib/SDEanalysis.py
sdelib/SDEint.py
sdelib/SDEproblem.py
sdelib/SDEspecification.py
sdelib/__init__.py
sdelib/convergence.py
sdelib/gui.py
sdelib/wpd.py
sdelib/wpd2.py
sdelib.egg-info/PKG-INFO
sdelib.egg-info/SOURCES.txt
sdelib.egg-info/dependency_links.txt
sdelib.egg-info/top_level.txt
sdelib/GUI/FullExampSpec.py
sdelib/GUI/Operation.jpg
sdelib/GUI/Operation.png
sdelib/GUI/Operation.qrc
sdelib/GUI/calcSolver.py
sdelib/GUI/chooseSolvers.py
sdelib/GUI/mainWin.py
sdelib/GUI/newF.py
sdelib/GUI/newFunc.py
sdelib/GUI/newG.py
sdelib/GUI/newReal.py
sdelib/GUI/newSpec.py
sdelib/GUI/probRealActions.py
sdelib/GUI/solActions.py
sdelib/GUI/solPlot.py