Metadata-Version: 1.1
Name: sdelib
Version: 0.905
Summary: Performs various actions on Ito SDEs
Home-page: https://github.com/perhauan/sdelib
Author: Per Hauan
Author-email: perman07@hotmail.com
License: UNKNOWN
Download-URL: https://github.com/perhauan/sdelib/archive/master.zip
Keywords: SDE,Ito,convergence,stability
Platform: UNKNOWN
Classifier: Programming Language :: Python
Classifier: Programming Language :: Python :: 3
Classifier: Development Status :: 4 - Beta
Classifier: Intended Audience :: Science/Research
Classifier: License :: OSI Approved :: MIT License
Classifier: Operating System :: OS Independent
Classifier: Topic :: Scientific/Engineering :: Mathematics
